{
  "视频类": [
    "KVM分频器切换器",
    "采集卡",
    "分离器",
    "分配器",
    "扩展坞",
    "切换器",
    "投屏器",
    "投频器",
    "延长器",
    "转换器",
    "转换线",
    "转接头"
  ],
  "蓝牙类": [
    "触控板",
    "触控笔",
    "电风扇",
    "电容笔",
    "定位器",
    "耳机",
    "发射器",
    "翻页笔",
    "防窥仪",
    "跟拍云台",
    "键盘",
    "鼠标",
    "键鼠套装",
    "接收发射器",
    "接收器",
    "蓝牙",
    "蓝牙适配器",
    "麦克风",
    "声卡",
    "适配器",
    "收发器",
    "收发射",
    "收发射器",
    "鼠标",
    "探测器",
    "头戴耳机",
    "无线耳机",
    "遥控器",
    "有线耳机",
    "转换器",
    "自拍杆"
  ],
  "数据类": [
    "USB共享切换器",
    "串口卡",
    "磁盘阵列",
    "读卡器",
    "对拷线",
    "分线器",
    "共享切换器",
    "集线器",
    "交换机",
    "扩展坞",
    "摄像头",
    "数据线",
    "网络分线器",
    "网络延长器",
    "无线网卡",
    "有线网卡",
    "硬盘盒"
  ],
  "音视频线类": [
    "AV线",
    "DP线",
    "DVI线",
    "HDMI线",
    "Micro HDMI线",
    "VGA线",
    "视频线",
    "转接头"

  ],
  "数据线类": [
    "数据线",
    "网线"
  ],
  "竞品-预研类": [

  ],
  "高频类": [
    "高频"
  ]
}
